picor/__init__.py
picor/cli.py
picor/isotope_correction.py
picor/isotope_probabilities.py
picor/isotopes.csv
picor/metabolites.csv
picor/resolution_correction.py
PICor-1.1.0.dist-info/AUTHORS.rst
PICor-1.1.0.dist-info/LICENSE.txt
PICor-1.1.0.dist-info/METADATA
PICor-1.1.0.dist-info/WHEEL
PICor-1.1.0.dist-info/entry_points.txt
PICor-1.1.0.dist-info/top_level.txt
PICor-1.1.0.dist-info/RECORD
