Metadata-Version: 2.1
Name: PICor
Version: 1.1.0
Summary: Isotope correction for MS data
Home-page: https://github.com/MolecularBioinformatics/PICor
Author: Jørn Dietze
Author-email: jorn.dietze@uit.no
License: gpl3
Platform: any
Classifier: Development Status :: 4 - Beta
Classifier: Programming Language :: Python
Requires-Python: >=3.6
License-File: LICENSE.txt
License-File: AUTHORS.rst
Requires-Dist: pandas
Requires-Dist: scipy
Requires-Dist: docopt
Requires-Dist: openpyxl
Provides-Extra: testing
Requires-Dist: pytest ; extra == 'testing'
Requires-Dist: pytest-cov ; extra == 'testing'
